{
  "proverbs": [
    {
      "display": "案ずるより産むが易し",
      "reading": "あんずるよりうむがやすし",
      "korean": "걱정하는 것보다 막상 해보면 쉽다."
    },
    {
      "display": "石の上にも三年",
      "reading": "いしのうえにもさんねん",
      "korean": "돌 위에서도 3년, 참고 견디면 반드시 성공한다."
    },
    {
      "display": "急がば回れ",
      "reading": "いそがばまわれ",
      "korean": "급할수록 돌아가라."
    },
    {
      "display": "嘘も方便",
      "reading": "うそもほうべん",
      "korean": "거짓말도 방편(때로는 필요하다)."
    },
    {
      "display": "馬の耳に念仏",
      "reading": "うまのみみにねんぶつ",
      "korean": "말의 귀에 염불(우이독경)."
    },
    {
      "display": "海老で鯛を釣る",
      "reading": "えびでたいをつる",
      "korean": "새우로 도미를 낚다(적은 투자로 큰 이익을 얻다)."
    },
    {
      "display": "縁の下の力持ち",
      "reading": "えんのしたのちからもち",
      "korean": "보이지 않는 곳에서 애쓰는 사람."
    },
    {
      "display": "岡目八目",
      "reading": "おかめはちもく",
      "korean": "당사자보다 제삼자가 더 잘 본다(훈수꾼이 더 잘 본다)."
    },
    {
      "display": "鬼に金棒",
      "reading": "おににかなぼう",
      "korean": "도깨비에게 방망이(금상첨화, 호랑이에게 날개)."
    },
    {
      "display": "終わり良ければ全て良し",
      "reading": "おわりよければすべてよし",
      "korean": "끝이 좋으면 다 좋은 것이다."
    },
    {
      "display": "継続は力なり",
      "reading": "けいぞくはちからなり",
      "korean": "계속하는 것이 힘이다(꾸준함이 실력이다)."
    },
    {
      "display": "弘法にも筆の誤り",
      "reading": "こうぼうにもふでのあやまり",
      "korean": "원숭이도 나무에서 떨어진다(전문가도 실수할 때가 있다)."
    },
    {
      "display": "猿も木から落ちる",
      "reading": "さるもきからおちる",
      "korean": "원숭이도 나무에서 떨어진다."
    },
    {
      "display": "三人寄れば文殊の知恵",
      "reading": "さんにんよればもんじゅのちえ",
      "korean": "세 사람이 모이면 좋은 지혜가 나온다."
    },
    {
      "display": "初心忘るべからず",
      "reading": "しょしんわするべからず",
      "korean": "초심을 잊지 마라."
    },
    {
      "display": "善は急げ",
      "reading": "ぜんはいそげ",
      "korean": "좋은 일은 서둘러라."
    },
    {
      "display": "千里の道も一歩から",
      "reading": "せんりのみちもいっぽから",
      "korean": "천 리 길도 한 걸음부터."
    },
    {
      "display": "備えあれば憂いなし",
      "reading": "そなえあればうれいなし",
      "korean": "유비무환(준비가 있으면 근심이 없다)."
    },
    {
      "display": "棚からぼた餅",
      "reading": "たなからぼたもち",
      "korean": "선반에서 떡 떨어지기(뜻밖의 행운)."
    },
    {
      "display": "塵も積もれば山となる",
      "reading": "ちりもつもればやまとなる",
      "korean": "티끌 모아 태산."
    },
    {
      "display": "灯台下暗し",
      "reading": "とうだいもとくらし",
      "korean": "등잔 밑이 어둡다."
    },
    {
      "display": "捕らぬ狸の皮算用",
      "reading": "とらぬたぬきのかわざんよう",
      "korean": "떡 줄 사람은 생각지도 않는데 김칫국부터 마신다."
    },
    {
      "display": "どんぐりの背比べ",
      "reading": "どんぐりのせくらべ",
      "korean": "도토리 키 재기."
    },
    {
      "display": "情けは人のためならず",
      "reading": "なさけはひとのためならず",
      "korean": "친절은 남을 위한 것만이 아니라 결국 자신에게 돌아온다."
    },
    {
      "display": "七転び八起き",
      "reading": "ななころびやおき",
      "korean": "칠전팔기."
    },
    {
      "display": "習うより慣れろ",
      "reading": "ならうよりなれろ",
      "korean": "배우기보다 익숙해져라."
    },
    {
      "display": "二階から目薬",
      "reading": "にかいからめぐすり",
      "korean": "2층에서 안약 넣기(일이 뜻대로 되지 않아 답답함)."
    },
    {
      "display": "二兎を追う者は一兎をも得ず",
      "reading": "にとをおうものはいっとをもえず",
      "korean": "두 마리 토끼를 잡으려다 한 마리도 못 잡는다."
    },
    {
      "display": "糠に釘",
      "reading": "ぬかにくぎ",
      "korean": "겨에 못 박기(아무런 반응이나 효과가 없음)."
    },
    {
      "display": "能ある鷹は爪を隠す",
      "reading": "のうあるたかはつめをかくす",
      "korean": "능력 있는 매는 발톱을 숨긴다."
    },
    {
      "display": "花より団子",
      "reading": "はなよりだんご",
      "korean": "금강산도 식후경(꽃보다 경단)."
    },
    {
      "display": "早起きは三文の徳",
      "reading": "はやおきはさんもんのとく",
      "korean": "일찍 일어나는 새가 벌레를 잡는다."
    },
    {
      "display": "人の振り見て我が振り直せ",
      "reading": "ひとのおりみてわがふりなおせ",
      "korean": "남의 행동을 보고 자신의 행동을 고쳐라."
    },
    {
      "display": "百聞は一見に如かず",
      "reading": "ひゃくぶんはいっけんにしかず",
      "korean": "백문이 불여일견."
    },
    {
      "display": "失敗は成功の母",
      "reading": "しっぱいはせいこうのはは",
      "korean": "실패는 성공의 어머니."
    },
    {
      "display": "覆水盆に返らず",
      "reading": "ふくすいぼんにかえらず",
      "korean": "엎질러진 물은 다시 담을 수 없다."
    },
    {
      "display": "身から出た錆",
      "reading": "みからでたさび",
      "korean": "자업자득."
    },
    { "display": "三日坊主", "reading": "みっかぼうず", "korean": "작심삼일." },
    {
      "display": "餅は餅屋",
      "reading": "もちわもちや",
      "korean": "떡은 떡집에서(전문가에게 맡겨라)."
    },
    {
      "display": "類は友を呼ぶ",
      "reading": "るいわともをよぶ",
      "korean": "유유상종."
    },
    {
      "display": "笑う門には福来たる",
      "reading": "わらうかどにはふくきたる",
      "korean": "웃으면 복이 와요."
    },
    {
      "display": "可愛い子には旅をさせよ",
      "reading": "かわいいこにはたびをさせよ",
      "korean": "귀한 자식일수록 고생을 시켜라."
    },
    {
      "display": "聞くは一時の恥、聞かぬは一生の恥",
      "reading": "きくはいっときのはじ、きかぬはいっしょうのはじ",
      "korean": "묻는 것은 한때의 부끄러움이나, 묻지 않는 것은 평생의 부끄러움이다."
    },
    {
      "display": "豚に真珠",
      "reading": "ぶたにしんじゅ",
      "korean": "돼지 목에 진주."
    },
    {
      "display": "井の中の蛙大海を知らず",
      "reading": "いのなかのかわずたいかいをしらず",
      "korean": "우물 안 개구리."
    },
    {
      "display": "雨降って地固まる",
      "reading": "あめふってじかためる",
      "korean": "비 온 뒤에 땅이 굳어진다."
    },
    {
      "display": "油断大敵",
      "reading": "ゆだんたいてき",
      "korean": "방심은 금물(방심이 큰 적)."
    },
    { "display": "自業自得", "reading": "じごうじとく", "korean": "자업자득." },
    {
      "display": "十人十色",
      "reading": "じゅうにんといろ",
      "korean": "십인십색(사람마다 제각각)."
    },
    {
      "display": "石橋を叩いて渡る",
      "reading": "いしばしをたたいてわたる",
      "korean": "돌다리도 두들겨 보고 건너라."
    },
    {
      "display": "一期一会",
      "reading": "いちごいちえ",
      "korean": "평생에 단 한 번뿐인 만남."
    },
    {
      "display": "一石二鳥",
      "reading": "いっせきにちょう",
      "korean": "일석이조."
    },
    {
      "display": "一難去ってまた一難",
      "reading": "いちなんさってまたいちなん",
      "korean": "산 넘어 산."
    },
    {
      "display": "一寸先は闇",
      "reading": "いっすんさきはやみ",
      "korean": "한 치 앞은 어둠(앞날은 알 수 없다)."
    },
    {
      "display": "犬猿の仲",
      "reading": "けんえんのなか",
      "korean": "견원지간(앙숙)."
    },
    {
      "display": "言わぬが花",
      "reading": "いわぬがはな",
      "korean": "말하지 않는 것이 낫다(침묵이 금)."
    },
    {
      "display": "噓つきは泥棒の始まり",
      "reading": "うそつきはどろぼうのはじまり",
      "korean": "바늘 도둑이 소 도둑 된다(거짓말은 도둑질의 시작)."
    },
    {
      "display": "得手に帆を揚げる",
      "reading": "えてにほをあげる",
      "korean": "기회를 잘 타다."
    },
    {
      "display": "海を山にする",
      "reading": "うみをやまにする",
      "korean": "불가능한 일을 하려 하다."
    },
    {
      "display": "金の切れ目が縁の切れ目",
      "reading": "かねのきれめがえんのきれめ",
      "korean": "돈 떨어지면 정도 떨어진다."
    },
    {
      "display": "壁に耳あり障子に目あり",
      "reading": "かべにみみありしょうじにめあり",
      "korean": "낮말은 새가 듣고 밤말은 쥐가 듣는다."
    },
    {
      "display": "果報は寝て待て",
      "reading": "かほうはねてまて",
      "korean": "진인사대천명(운은 때를 기다려야 한다)."
    },
    {
      "display": "口は災いの元",
      "reading": "くちはわざわいのもと",
      "korean": "입은 화의 근원."
    },
    {
      "display": "苦労は買ってでもせよ",
      "reading": "くろうはかってでもせよ",
      "korean": "젊어서 고생은 사서도 한다."
    },
    {
      "display": "光陰矢の如し",
      "reading": "こういんやのごとし",
      "korean": "시간은 화살과 같이 빠르다."
    },
    {
      "display": "後悔先に立たず",
      "reading": "こうかいさきにたたず",
      "korean": "후회해도 소용없다."
    },
    {
      "display": "ごまをする",
      "reading": "ごまをする",
      "korean": "아부하다(깨를 갈다)."
    },
    {
      "display": "転ばぬ先の杖",
      "reading": "ころばぬさきのつえ",
      "korean": "넘어지기 전의 지팡이(사전 준비)."
    },
    {
      "display": "釈迦に説法",
      "reading": "しゃかにせっぽう",
      "korean": "공자 앞에서 문자 쓰기."
    },
    {
      "display": "朱に交われば赤くなる",
      "reading": "しゅにまじわればあかくなる",
      "korean": "근묵자흑(나쁜 친구를 사귀면 나빠진다)."
    },
    {
      "display": "知らぬが仏",
      "reading": "しらぬがほとけ",
      "korean": "모르는 게 약이다."
    },
    {
      "display": "好きこそ物の上手なれ",
      "reading": "すきこそもののじょうずなれ",
      "korean": "좋아하는 일일수록 잘하게 된다."
    },
    {
      "display": "住めば都",
      "reading": "すめばみやこ",
      "korean": "정들면 고향(살다 보면 그곳이 제일이다)."
    },
    {
      "display": "雀の涙",
      "reading": "すずめのなみだ",
      "korean": "쥐꼬리만 하다(참새의 눈물)."
    },
    {
      "display": "背に腹はかえられない",
      "reading": "せにはらはかえられない",
      "korean": "다급한 나머지 다른 것을 돌아볼 여유가 없다."
    },
    {
      "display": "袖振り合うも多生の縁",
      "reading": "そでふりあうもたしょうのえん",
      "korean": "옷깃만 스쳐도 인연이다."
    },
    {
      "display": "立て板に水",
      "reading": "たていたにみず",
      "korean": "거침없이 말하다(청산유수)."
    },
    {
      "display": "血は水よりも濃い",
      "reading": "ちはみずよりもこい",
      "korean": "피는 물보다 진하다."
    },
    {
      "display": "釣り落とした魚は大きい",
      "reading": "つりおとしたさかなはおおきい",
      "korean": "놓친 고기가 더 커 보인다."
    },
    {
      "display": "出る杭は打たれる",
      "reading": "でるくいはうたれる",
      "korean": "모난 돌이 정 맞는다."
    },
    {
      "display": "時に利あらず",
      "reading": "ときにりあらず",
      "korean": "운이 따르지 않다."
    },
    {
      "display": "飛んで火に入る夏の虫",
      "reading": "とんでひにいるなつのむし",
      "korean": "불나방(스스로 화를 자초함)."
    },
    {
      "display": "虎の威を借る狐",
      "reading": "とらのいをかるきつね",
      "korean": "호가호위."
    },
    {
      "display": "どん底から這い上がる",
      "reading": "どんぞこからはいあがる",
      "korean": "밑바닥에서 일어서다."
    },
    {
      "display": "無い袖は振れない",
      "reading": "ないそではふれない",
      "korean": "가진 게 없으면 내놓을 것도 없다."
    },
    {
      "display": "泣きっ面に蜂",
      "reading": "なきっつらにはち",
      "korean": "설상가상."
    },
    {
      "display": "生兵法は大怪我の元",
      "reading": "なまびょうほうはおおけがのもと",
      "korean": "선무당이 사람 잡는다."
    },
    {
      "display": "喉元過ぎれば熱さを忘れる",
      "reading": "のどもとすぎればあつさをわすれる",
      "korean": "화장실 갈 때와 올 때 마음이 다르다."
    },
    {
      "display": "乗り掛かった舟",
      "reading": "のりかかったふね",
      "korean": "이미 시작한 일(중단할 수 없는 상황)."
    },
    {
      "display": "火の無い所に煙は立たぬ",
      "reading": "ひのないところにけむりはたたぬ",
      "korean": "아니 뗀 굴뚝에 연기 날까."
    },
    {
      "display": "火に油を注ぐ",
      "reading": "ひにあぶらをそそぐ",
      "korean": "불난 집에 부채질하다."
    },
    {
      "display": "瓢箪から駒が出る",
      "reading": "ひょうたんからこまがでる",
      "korean": "농담이 진담 된다(생각지도 못한 일이 일어남)."
    },
    {
      "display": "貧乏暇なし",
      "reading": "びんぼうひまなし",
      "korean": "가난할수록 쉴 틈이 없다."
    },
    {
      "display": "仏の顔も三度",
      "reading": "ほとけのかおもさんど",
      "korean": "아무리 착한 사람도 한계가 있다."
    },
    {
      "display": "待てば海路の日和あり",
      "reading": "まてばかいろのひよりあり",
      "korean": "기다리면 좋은 날이 온다(고진감래)."
    },
    {
      "display": "身の程を知る",
      "reading": "みのほどをしる",
      "korean": "분수를 알다."
    },
    {
      "display": "百日の説法屁一つ",
      "reading": "ひゃくにちのせっぽうへひとつ",
      "korean": "공든 탑이 무너지랴(잘 하다가 한 번의 실수로 망침)."
    },
    {
      "display": "目には目を、歯には歯を",
      "reading": "めにはめを、はにははを",
      "korean": "눈에는 눈, 이에는 이."
    },
    {
      "display": "弱り目に祟り目",
      "reading": "よわりめにたたりめ",
      "korean": "엎친 데 덮친 격."
    },
    {
      "display": "来年の事を言えば鬼が笑う",
      "reading": "らいねんのことをいえばおにがわらう",
      "korean": "내일 일은 아무도 모른다."
    }
  ]
}
